uastyle/__config__.py
uastyle/__init__.py
uastyle/__main_imports__.py
uastyle/apply_colors.py
uastyle/constants.py
uastyle/utils.py
uastyle-0.2.1.dist-info/LICENSE
uastyle-0.2.1.dist-info/METADATA
uastyle-0.2.1.dist-info/WHEEL
uastyle-0.2.1.dist-info/top_level.txt
uastyle-0.2.1.dist-info/RECORD
