Metadata-Version: 2.2
Name: uastyle
Version: 0.2.1
Summary: Ukrainian colors for matplotlib
Home-page: https://github.com/kyrylo-gr/uastyle
Author: kyrylo.gr
Author-email: git@kyrylo.gr
Classifier: Programming Language :: Python :: 3
Classifier: Operating System :: OS Independent
Requires-Python: >=3.7
License-File: LICENSE
Requires-Dist: matplotlib
Dynamic: author
Dynamic: author-email
Dynamic: classifier
Dynamic: description
Dynamic: description-content-type
Dynamic: home-page
Dynamic: requires-dist
Dynamic: requires-python
Dynamic: summary
